{
    "text": "сборка получив команду на сборку облако amvera ищет в папке code конфигурационный файл configuration config file md amvera yaml возможны три ситуации 1 отсутствует amvera yaml но удается найти dockerfile начинается сборка образа используя dockerfile процесс описан в этом разделе configuration docker md 2 отсутствует и amvera yaml и dockerfile сборка завершается ошибкой 3 присутствует amvera yaml начинается сборка приложения процесс сборки с amvera yaml build proc img build proc png облако amvera считывает раздел meta из файла конфигурации amvera yaml и ищет подходящий инструмент для сборки в списке поддерживаемых окружений supported env rst под инструментом для сборки подразумевается готовый образ с установленным в него компилятором интерпретатором который используется для создания контейнера сборки при создании контейнера в него монтируются папки code и artifacts во время работы контейнера происходит запуск инструмента сборки для выбранного окружения с указанными в секции build параметрами запуск команды выполняется в папке code storage md code после чего файлы необходимые для работы приложения копируются в папку artifacts storage md artifacts в процессе сборки статус приложения будет выполняется сборка в случае если сборка выполнилась успешно статус сменится на проект развертывается и облако amvera автоматически инициализирует процесс запуска приложения если сборка завершилась с ошибкой то следует обратиться к логам сборки лог сборки eval rst admonition важно class warning сборка приложения осуществляется в дополнительном контейнере тарифицирующемся так же как и само приложение из за чего текущее количество работающих инстансов может быть больше требуемого инициализация сборки eval rst admonition важно class warning во время сборки уже запущенные реплики приложения продолжают работать что обеспечивает накатывание обновлений с минимальным dos автоматическая сборка сборка начинается автоматически если был совершен пуш в master ветку git репозитория git rst амвера так же сборка приложения автоматически начинается после завершения процесса создания приложения в том случае если была выбрана опция загрузки файлов через интерфейс ручная сборка в том случае если требуется вручную инициализировать процесс сборки приложения это можно сделать двумя способами 1 если приложение ранее собиралось то будет доступна кнопка пересобрать проект в панели инструментов на странице приложения rebuild img rebuild png 2 если проект ранее не собирался или указанная выше кнопка по какой либо причине не активна можно перейти в раздел конфигурация в этом разделе при наличии заполненной конфигурации configuration config file md внизу будет доступна кнопка собрать configuration img configuration png лог сборки для отслеживания процесса сборки следует воспользоваться консолью вывода логов которая находится во вкладке лог сборки загрузка логов может занимать некоторое время и работать с задержкой для загрузки логов необходимо нажать на кнопку загрузить историю которая расположена в нижнем правом углу окна логов и выглядит как циферблат load logs img load logs png eval rst admonition важно class warning если процесс сборки завершился с ошибкой и лог остается пустым при нескольких попытках его загрузить следует проверить правильность заполнения секции build конфигурационного файла",
    "metadata": {
        "file_name": "build.md",
        "section_count": 6,
        "section_1": "Сборка",
        "section_2": "Процесс сборки с `amvera.yaml`",
        "section_3": "Инициализация сборки",
        "section_4": "Автоматическая сборка",
        "section_5": "Ручная сборка",
        "section_6": "Лог сборки"
    }
}