{
    "text": "файл конфигурации для настройки сборки build md и запуска run md проекта можно создать файл amvera yml или amvera yaml в корне репозитория альтернативой является использование dockerfile docker создать amvera yaml лучше всего в интерфейсе приложения в разделе конфигурация так он автоматически добавится в корень проекта создав при этом новый коммит в гит репозиторий возможно так же воспользоваться нашим генератором yaml перейдя по ссылке https manifest amvera ru либо самостоятельно используя инструкции ниже если файл конфигурации отсутствует то amvera будет искать файл dockerfile docker если dockerfile будет найден он будет использоваться для сборки если dockerfile также не будет найден сборка завершится провалом в дальнейшем на файл amvera yml или amvera yaml для определенности будем ссылаться как amvera yaml структура конфигурационного файла файл amvera yaml состоит из трех секций meta секция meta определяет общую информацию о сборке такую как окружение и инструменты сборки со списком поддерживаемых окружений и подробным их описанием можно ознакомиться на этой странице supported env rst пример секции meta для jvm приложения собираемого при помощи maven yaml meta environment jvm toolchain name maven version 17 подробнее о сборке jvm приложений с помощью maven в сервисе amvera можно прочитать здесь environments jvm maven md build секция build определяет параметры необходимые для сборки приложения build md для разных окружений эти параметры разные про параметры для вашего окружения можно прочитать в соответствующем разделе данной документации если указывать параметры сборки не нужно то секцию build можно опустить в нашем примере сборки jvm приложения при помощи maven все параметры build являются необязательными однако если нужно указать дополнительные параметры компиляции сделать это можно следующим образом yaml build args dserver port 80 pproduction run секция run определяет параметры необходимые для запуска приложения run md аналогично сборке для разных окружения эти параметры разные и описаны в соответствующем разделе данной документации так параметр persistencemount задает то в какую папку будет примонтировано постоянное хранилище storage md data иными словами если там указано data то именно по этому пути следует сохранять важные файлы во время работы приложения если указывать параметры запуска не нужно то секцию run можно опустить в нашем примере сборки jvm приложения при помощи maven в секции run необходимо как минимум указать путь до jar файла относительно корня проекта yaml run jarname bag end jar пример так весь файл amvera yaml для нашего примера выглядит следующим образом yaml meta environment jvm toolchain name maven version 17 build args dserver port 80 pproduction run jarname bag end jar так как формат файла конфигурации yaml секции можно указывать в любом порядке",
    "metadata": {
        "file_name": "config-file.md",
        "section_count": 6,
        "section_1": "Файл конфигурации",
        "section_2": "Структура конфигурационного файла",
        "section_3": "meta",
        "section_4": "build",
        "section_5": "run",
        "section_6": "Пример"
    }
}