{
    "text": "mysql beta облако amvera поддерживает создание управляемого кластера mysql с одной или несколькими запущенными репликами создание кластера происходит в несколько простых шагов разворачивание кластера 1 на главной странице нажать на кнопку создать 2 выбрать тип сервиса преднастроенное приложение из маркетплейса 3 выбрать параметр сервиса базы данных и сервис mysql 4 ввести произвольное название проекта и выбрать подходящий тариф eval rst admonition внимание class attention работа возможна на тарифе не ниже начальный если вам требуется создание бэкапов то необходимо повысить тариф до начальный плюс 3 задать параметры субд mysql mysql database имя создаваемой базы данных mysql root password пароль для root пользователя eval rst admonition важно class warning это пароль для пользователя root который будеть иметь доступ ко всем бд и права на любые действия пароль необходимо запомнить его будет невозможно восстановить или изменить mysql user имя создаваемого пользователя mysql mysql password пароль для вышеуказанного пользователя eval rst admonition важно class warning тарификация происходит отдельно за каждую реплику согласно выбранному тарифу 4 нажать кнопку завершить и дождаться перехода кластера в статус приложение запущено добавление бд после создания кластера по дефолту будет создана бд mysql или та что была указана в параметре mysql database которая доступна для полноценной работы eval rst admonition важно class warning имя бд может состоять только из a z a z 0 9 и бэкапы бэкапы по расписанию сервис предоставляет возможность создания бесплатных бэкапов по расписанию бэкапы начнут создаваться со следующего дня в час их активации сервис хранит крайние ins три ins бэкапа бэкапы по клику для создания бэкапа нажмите на кнопку создать бэкап и введите его описание чтобы отличить его от других имя бэкапа будет сгенерировано автоматически максимально вы можете создать ins три ins бэкапа они также являются бесплатными backups img mysql backups png восстановление кластера eval rst admonition внимание class attention восстановление кластера повлечет за собой потерю несохраненных данных убедитесь что у вы создали бэкап требуемого состояния перед восстановлением из другого бэкапа восстановить кластер можно по клику на иконку необходимого бэкапа во время восстановления ваш кластер остановится и запустится автоматически в течении этого времени он будет недоступен restore img mysql restore png подключение к кластеру eval rst admonition внимание class attention подключение к базе данных возможно только из других проектов созданных в amvera для доступа к базе данных из других проектов амвера необходимо указать доменное имя которое находится на вкладке инфо internal domain img mysql internal domain png развертывание phpmyadmin 1 создать приложение с подходящим тарифом eval rst admonition внимание class attention для работы phpmyadmin требуется выбрать тариф начальный phpmyadmin create img phpmyadmin create png 2 указать необходимые переменные окружения в разделе переменные у проекта необходимо задать следующие переменные окружения applications configuration variables md переменная pma absolute uri ссылка на приложение в формате https транслитерированное имя проекта имя пользователя amvera io переменная pma arbitrary установленная в 1 phpmyadmin variables img phpmyadmin variables png 3 активировать в настройках бесплатное доменное имя applications configuration network md бесплатное доменное имя амвера или добавляем свое applications configuration network md свое доменное имя db create img pgadmin domain png eval rst admonition хитрость class hint чтобы экономить на потреблении проекта с phpmyadmin рекомендуем ставить его на паузу после окончания работы 4 подключиться к кластеру mysql phpmyadmin connect img phpmyadmin connect png введите внутренне доменное имя подключение к кластеру имя пользователя по дефолту создается пользователь root пароль пользователя для root пользователя вы устанавливали пароль при создании кластера eval rst admonition важно class warning доступ ко всем базам данных имеет только пользователь root вы можете зайти под иным созданным пользователем тогда будет открыт доступ только к той бд в которой он был создан phpmyadmin success img phpmyadmin success png видеопример как использовать mysql и phpmyadmin в amvera cloud eval rst youtube ofkja vnxuo align center width 100 в этом видео мы рассмотрим как использовать базу данных mysql в amvera cloud как развернуть базу данных mysql как подключаться к базе данных mysql из других приложений как использовать phpmyadmin для управления базами данных mysql таймкоды 00 00 интро 00 34 развертывание mysql 01 28 развертывание phpmyadmin 02 47 подключение к бд из другого проекта 05 04 проверка работоспособности",
    "metadata": {
        "file_name": "mysql-beta.md",
        "section_count": 14,
        "section_1": "MySQL (beta)",
        "section_2": "Разворачивание кластера",
        "section_3": "Добавление БД",
        "section_4": "Бэкапы",
        "section_5": "Бэкапы по расписанию",
        "section_6": "Бэкапы по клику",
        "section_7": "Восстановление кластера",
        "section_8": "Подключение к кластеру",
        "section_9": "Развертывание phpMyAdmin",
        "section_10": "1. Создать приложение с подходящим тарифом.",
        "section_11": "2. Указать необходимые переменные окружения.",
        "section_12": "3. Активировать в настройках [бесплатное доменное имя](../applications/configuration/network.md#бесплатное-доменное-имя-амвера) или [добавляем свое](../applications/configuration/network.md#свое-доменное-имя). ",
        "section_13": "4. Подключиться к кластеру MySQL",
        "section_14": "Видеопример как использовать MySQL и phpMyAdmin в Amvera Cloud"
    }
}