{
    "text": "тарифные планы все тарифы amvera имеют поминутную тарификацию со списанием раз в час если ваш проект проработал 12 минут средства будут списаны только за эти 12 минут все тарифные планы кроме дополнительных дисков можно менять как в большую так и в меньшую сторону списания происходят только в случае потребления проектом ресурса если проект находится в статусе запущен запускается или работает с ошибкой биллинг будет тарифицировать данное время если проект в статусе остановлен или заморожен и объем файлов проекта не превышает заданный тариф списания не производятся допускается превышение тарифов по выделенному диску с тарификацией разницы потребления ваши проекты не остановятся если вы заполните хранилище в рамках тарифа тарифы для приложений пробный 0 1 цпу 100 мб озу 2 гб ssd 0 24 руб в час 170 руб 30 дней начальный 0 25 цпу 500 мб озу 5 гб ssd 0 4 руб в час 290 руб 30 дней дополнительно позволяет получить как и старшие тарифы гарантии в рамках sla начальный плюс 0 5 цпу 1 гб озу 7 гб ssd 0 68 руб в час 490 руб 30 дней тариф начальный плюс и старшие тарифы дополнительно позволяют получить доступ к бэкапам и расширенному мониторингу стандартный 1 цпу 2 5 гб озу 15 гб ssd 2 01 руб в час 1450 руб 30 дней тарифы стандартный и выше дополнительно позволяют получить доступ к приоритетной персонализированной поддержке ультра 2 цпу 6 гб озу 25 гб ssd 5 97 руб в час 4300 руб 30 дней ультра плюс 3 цпу 9 гб озу 35 гб ssd 10 76 руб в час 7750 руб 30 дней тарифы для субд и преднастроенных сервисов начальный 0 25 цпу 500 мб озу 5 гб ssd 0 4 руб в час 290 руб 30 дней начальный плюс 0 5 цпу 1 гб озу 7 гб ssd 0 68 руб в час 490 руб 30 дней стандартный 1 цпу 2 5 гб озу 15 гб ssd 2 01 руб в час 1450 руб 30 дней ультра 2 цпу 6 гб озу 25 гб ssd 5 97 руб в час 4300 руб 30 дней ультра плюс 3 цпу 9 гб озу 35 гб ssd 10 76 руб в час 7750 руб 30 дней тарифы для диска тарифицируется только превышение потребления лимита по тарифу тарифицируется фактическое превышение относительно тарифа стоимость каждого гб сверх тарифа составляет 35 руб за 720 часов 30 дней хранения в расчет потребления диска входят все файлы проекта из папок code artifacts data repo правила заморозки и удаления проектов при остановке проекта из за отрицательного баланса либо самостоятельной остановке проект автоматически будет заморожен удалены артефакт через 30 дней остановки проекта при этом если объем файлов проекта после его заморозки превышает выделенный лимит по выбранному тарифу проект может быть удален гарантированно избежать удаления проекта после 30 дней заморозки поможет поддержание баланса в положительной зоне",
    "metadata": {
        "file_name": "price.md",
        "section_count": 5,
        "section_1": "Тарифные планы",
        "section_2": "Тарифы для приложений",
        "section_3": "Тарифы для СУБД и преднастроенных сервисов",
        "section_4": "Тарифы для диска",
        "section_5": "Правила заморозки и удаления проектов"
    }
}