{
    "text": "быстрый старт amvera стремиться сделать доставку кода и развертывания приложения максимально простым и понятным код своего приложения можно загружать двумя способами 1 используя git репозиторий подробно о работе с git и использованием репозиториев написано в соответствующем разделе git rst 2 через интерфейс всегда можно загрузить нужные файлы в удобном графическом окне процесс создания приложения инициализация 1 перейдите в личный кабинет amvera https cloud amvera ru при необходимости авторизовавшись 2 для открытия формы создания приложения необходимо нажать кнопку создать 3 в появившемся окне требуется указать название для вашего приложения выбрать тип сервиса приложение необходимый тарифный план и нажать далее quick start1 img quick start1 png 4 после окончания индикатора загрузки приложение будет создано и откроется следующий этап создания проекта загрузка данных загрузка данных для хранения пользовательского кода вне зависимости от метода загрузки используется git git rst репозиторий при использовании загрузки через интерфейс всегда можно переключиться на доставку кода через git и наоборот загрузка через git для загрузки данных приложения с использованием git потребуется 1 привязать к amvera свой репозиторий или склонировать созданный в amvera информация о том как это сделать находится в разделе git git rst этой документации предположим что на локальном компьютере ещё нет git репозитория выполним команду указанную первой на текущей странице shell git clone https git amvera ru username service slug quick start2 img quick start2 png теперь на локальном компьютере есть папка связанная с удалённым репозиторием amvera в эту папку нужно скопировать код проекта 2 создать файл конфигурации подробно о том что такое файл конфигурации и зачем он нужен можно найти в соответсвующем разделе configuration config file md сгенерировать файл конфигурации через генератор yaml файла https manifest amvera ru воспользоваться следующим шагом создания проекта потребуется сделать git pull в некоторых случаях может потребоваться написать файл самостоятельно инструкцию для вашего окружения можно найти на странице поддерживаемых окружений supported env rst если нужно воспользоваться сборкой и запуском dockerfile то это описано тут configuration docker md eval rst admonition важно class warning сгенерированный файл конфигурации нужно положить в корневую папку репозитория 3 создать файл с зависимостями прописать корректно все зависимости в файл чтобы наше облако смогло их установить eval rst admonition важно class warning для python необходимо наличие файла requirements txt с требуемыми библиотеками 4 сделать push в master ветку если все шаги выполнены правильно ваш проект автоматически соберется build md и развернется run md после отправки кода в master загрузка через интерфейс для развертывания через интерфейс необходимо загрузить файлы проекта в том числе файл с необходимыми зависимостями eval rst admonition важно class warning для python необходимо наличие файла requirements txt с требуемыми библиотеками после того как файлы были перетянуты нужно дождаться их появления списка загруженных файлов и проверить что ничего не потерялось quick start2 img quick start4 png задание конфигурации конфигурацию configuration config file md можно задать используя последний этап при создании приложения требуется выбрать используемое вашим приложением окружение и инструмент чтобы лучше ознакомится с вводимыми параметрами следует ознакомиться с необходимым окружением в данном разделе supported env rst quick start2 img quick start5 png eval rst admonition важно class warning поскольку файл конфигурации хранится в том же репозитории что и код то его добавление создает новый commit в репозиторий amvera если используется git необходимо будет сделать pull чтобы забрать его локально после нажатия кнопки завершить при условии загрузки файлов через интерфейс начнется сборка и впоследствии запуск приложения примеры примеры развертывания проектов для разных стеков находятся в разделе примеры general examples rst если вы столкнулись с ошибкой или вам что то непонятно ознакомьтесь с разделом частые ошибки general faq rst мы постарались собрать самые частые ошибки возникающие у наших пользователей пишите в поддержку на почту support amvera ru мы обязательно ответим и постараемся вам помочь обычно ответ занимает от 5 минут до суток если ничего не помогает вы можете написать нашему ceo кириллу косолапову на почту kkosolapov amvera ru отвечает он дольше чем поддержка но обязательно с вами свяжется и поможет решить ваш вопрос",
    "metadata": {
        "file_name": "quick-start.md",
        "section_count": 9,
        "section_1": "Быстрый старт",
        "section_2": "Процесс создания приложения",
        "section_3": "Инициализация",
        "section_4": "Загрузка данных",
        "section_5": "Загрузка через git",
        "section_6": "Загрузка через интерфейс",
        "section_7": "Задание конфигурации",
        "section_8": "Примеры",
        "section_9": "Если вы столкнулись с ошибкой или вам что-то непонятно"
    }
}