{
    "text": "ruby rails данная конфигурация подходит если проект собирается при помощи ruby написать yaml файл можно как самостоятельно используя инструкцию ниже так и воспользоваться нашим генератором yaml перейдя по ссылке https manifest amvera ru либо заполнить в разделе конфигурация личного кабинета секция meta секция meta файла amvera yml будет выглядеть следующим образом yaml meta environment ruby toolchain name bundle version 3 0 из параметров которые можно здесь менять это meta toolchain version логически это версия ruby которую нужно использовать для сборки технически значение version подставляется в имя образа docker который будет использован для фазы сборки и запуска это ruby meta toolchain version допустимые значения можно увидеть на странице докер хаба https hub docker com важно значение meta toolchain version должно быть допустимым как для фазы сборки так и для фазы запуска лучше всего подходит простой номер lts версии ruby секция build в секции build могут быть указаны следующие параметры image параметр image позволяет использовать другой образ для сборки а не тот который предлагается amvera образ должен удовлетворять следующим требованиям исходный код для сборки ожидается в папке app или образу без разницы где будет находиться исходный код секция run в секции run могут быть использованы следующие параметры image mainscript persistencemount containerport параметр image позволяет использовать другой образ для сборки а не тот который предлагается amvera образ должен удовлетворять следующим требованиям результат сборки ожидается в папке app или образу без разницы где будет находиться результат сборки параметр mainscript позволяет указать главный скрипт в проекте с расширением параметр persistencemount позволяет указать в какую директорию будет примонтирована папка с постоянным хранилищем storage md data по умолчанию имеет значение data параметр containerport позволяет указать какой порт слушает приложение по умолчанию имеет значение 80 важно если вы используете обычный ruby без каких либо фреймворков необходимо добавить файл в ваш проект gemfile в который добавить минимальную конфигурацию содержимое gemfile yaml source https rubygems org рецепты минимальный файл amvera yml yaml meta environment ruby toolchain name bundle version 3 0 run mainscript webservice rb",
    "metadata": {
        "file_name": "ruby-bundle.md",
        "section_count": 7,
        "section_1": "Ruby (Rails)",
        "section_2": "Секция meta",
        "section_3": "Секция build",
        "section_4": "Секция run",
        "section_5": "Важно",
        "section_6": "Рецепты",
        "section_7": "Минимальный файл amvera.yml"
    }
}