{
    "text": "запуск получив команду на запуск облако amvera ищет в папке code конфигурационный файл configuration config file md amvera yaml возможны три ситуации 1 отсутствует amvera yaml но удается найти dockerfile начинается запуск образа полученного в результате сборки dockerfile configuration docker md 2 отсутствует и amvera yaml и dockerfile запуск завершается ошибкой 3 присутствует amvera yaml начинается запуск приложения процесс запуска с amvera yaml build proc img run proc png облако amvera считывает раздел meta из файла конфигурации amvera yaml и ищет подходящий инструмент для запуска в списке поддерживаемых окружений supported env rst под инструментом для запуска подразумевается готовый образ с установленным в него программами которые позволят запустить приложение python jvm и т д выбранный благодаря конфигурации образ запускается в новом контейнере с параметрами указанными в секции run этой же конфигурации в процессе создания контейнера в него монтируются storage md две папки artifacts папка storage md artifacts с полученными в результате процесса сборки файлами может затираться при пересборке монтирование происходит в папку app запущенного контейнера data папка постоянного хранилища storage md data которую не затрагивает процесс сборки и следовательно файлы остаются нетронутыми для хранения получаемых в процессе работы программы данных таких как бд логи и т д необходимо использовать именно эту папку монтирование происходит в папку persistencemount заданную конфигурации по умолчанию data в процессе запуска статус приложения будет выполняется запуск который при успехе сменится на приложение запущено в случае если статус ошибка развертывания или проект долго висит в статусе выполняется запуск стоит искать проблему в секции run файла конфигурации жизненный цикл eval rst admonition важно class warning в первые минуты работы приложения статус может быть ошибка работы приложения так как приложение формально ещё не запустилось и амвера не может явно определить его точный статус amvera стремиться обеспечить бесперебойную работу развернутого приложения если приложение по какой либо причине завершает работу возникло исключение программа дошла до конца оно автоматически будет перезапущено если возникающая ошибка не дает проработать приложению больше минуты то статус приложения переходит в ошибка работы приложения однако облако продолжает пытаться его перезапустить снова и снова если впервые развернутое приложение находится в этом состояние больше получаса то оно автоматически останавливается и переходит в статус остановлено из за повторяющейся ошибки eval rst admonition важно class warning для профилактики ошибок работы приложения рекомендуем перейти во вкладку лог приложения остановка приложения если требуется на время остановить проект можно воспользоваться кнопкой включить выключить или задать желаемое кол во реплик равное нулю на панели инструментов при этом данные во всех папках остаются нетронутыми если приложение находится в выключенном статусе более 30 дней то оно автоматически замораживается заморозка приложения заморозка приложения если приложение больше не нужно но вы хотите сохранить данные в репозитории и в постоянном хранилище то можно воспользоваться кнопкой заморозить проект во вкладке настройки при заморозке полностью очищается папка artifacts а так же привязанные домены приложение переходит в статус заморожено для разморозки требуется инициализировать процесс сборки проекта и выставить кол во желаемых реплик general scaling md более нуля лог приложения для отслеживания работы приложения следует воспользоваться консолью вывода логов которая находится во вкладке лог приложения загрузка логов может занимать некоторое время и работать с задержкой для загрузки логов необходимо нажать на кнопку загрузить историю которая расположена в нижнем правом углу окна логов и выглядит как циферблат load logs img load logs png",
    "metadata": {
        "file_name": "run.md",
        "section_count": 6,
        "section_1": "Запуск",
        "section_2": "Процесс запуска с `amvera.yaml`",
        "section_3": "Жизненный цикл",
        "section_4": "Остановка приложения",
        "section_5": "Заморозка приложения",
        "section_6": "Лог приложения"
    }
}