{
    "text": "sla sla безотказной работы amvera cloud дает гарантию по доступности инфраструктуры на уровне 99 5 uptime в календарный месяц компенсации в рамках sla по uptime при нарушении со стороны amvera установленного порога uptime пользователи вправе претендовать на компенсацию в размере 20 от потребления ресурса пострадавшими проектами за прошедший месяц при этом компенсация не может превышать сумму пополнений баланса пользователем в прошлых периодах компенсация начисляется исключительно в виде предоставления гранта или промокода на пополнение баланса amvera денежные возвраты не осуществляются правила расчета uptime uptime распространяется исключительно на время безотказной работы инфраструктуры amvera и не распространяется на отказы на стороне кода приложений пользователей и отказы вызванные установкой настроек пользователями примеры если на стороне amvera упала сеть и сервисы не работают вы можете претендовать на компенсацию если наблюдается недоступность managed сервисов вы можете претендовать на компенсацию но если вы накатили обновление и приложение сломалось это не зона ответственности amvera если ваше приложение перестало работать но мы не наблюдаем неполадок в системе мы исходим из того что проблема на стороне кода настроек приложения проведение плановых работ на сервере и обновлений системы не подпадает под действие sla uptime рассчитывается на основе информации об инцидентах размещенных на официальных ресурсах amvera cloud и обращений в поддержку по адресу support amvera ru uptime в 99 5 допускает до 4 часов недоступности в месяц sla по сохранности данных amvera cloud дает гарантию по сохранности данных в постоянном хранилище data и данных в managed postgresql компенсации в рамках sla сохранности данных при потере данных в постоянном хранилище data или данных в managed postgresql по вине amvera пользователи вправе претендовать на компенсацию в размере 50 от стоимости потребления ресурса пострадавшими проектами за прошедший месяц при этом компенсация не может превышать сумму пополнений баланса пользователем в прошлых периодах компенсация начисляется исключительно в виде предоставления гранта или промокода на пополнение баланса amvera денежные возвраты не осуществляются правила получения компенсации для получения компенсации необходимо направить заявку на почту support amvera ru содержащую подробную информацию об инциденте после проверки заявки компенсация производится в течение 10 рабочих дней",
    "metadata": {
        "file_name": "sla.md",
        "section_count": 7,
        "section_1": "SLA",
        "section_2": "SLA безотказной работы",
        "section_3": "Компенсации в рамках SLA по uptime",
        "section_4": "Правила расчета uptime",
        "section_5": "SLA по сохранности данных ",
        "section_6": "Компенсации в рамках SLA сохранности данных",
        "section_7": "Правила получения компенсации"
    }
}