{
    "text": "пополнение счета eval rst admonition внимание class attention если у вас нет российской карты и вы используете иностранную карту следует использовать mastercard и пополнять на сумму от 1000 руб российские карты поддерживаются без ограничений если вы столкнулись со сложностями при пополнении пишите на почту support amvera ru мы обязательно поможем пополнение счета для юридических лиц для пополнения счета через банковский перевод направьте реквизиты организации и ник пользователя на почту support amvera ru мы выставим счет по которому можно произвести оплату зачисление производится в течении двух рабочих дней после поступления оплаты закрывающие документы направляются ежеквартально по почте россии пополнение счета для физических лиц амвера использует предоплатную модель работы поэтому для обеспечения бесперебойной работы контейнеров необходимо заранее пополнять баланс для этого на странице баланс https cloud amvera ru balance необходимо воспользоваться формой пополнения баланса topup img topup png укажите сумму на которую вы хотите пополнить баланс допускается целое значение в рублях после этого нажмите кнопку пополнить вы попадете на страницу оплаты сервиса робокасса robokassa img robokassa png введите свои данные для оплаты и нажмите кнопку оплатить если вы передумали можете нажать на ссылку amvera cloud в верхнем левом углу экрана либо просто закрыть страницу оплаты в случае успешной оплаты вас переместит на страницу со списком проектов к этому моменту оплата уже могла пройти и она отразится в вашем балансе тем не менее из за специфики банковских переводов деньги могут дойти позже если платеж не пришел в течение 15 минут свяжитесь с поддержкой amvera для выяснения причин промокоды если у вас имеется промокод для нашего сервиса amvera то перед пополнением баланса необходимо ввести промокод в соответсвующее поле и только после этого нажимать кнопку пополнить promo img promo png подключение автоплатежа отслеживание баланса и ручное пополнение через интерфейс может быть неудобным поэтому есть возможность подключить автоплатеж на заданную сумму на странице баланс https cloud amvera ru balance auto topup img auto topup png как это работает при пополнении баланса вы ставите галочку «автоплатеж» по умолчанию она выключена чтобы избежать случайной подписки задаете максимальное количество платежей в месяц это необходимо чтобы гарантировать списание не более определенной суммы пополняете баланс на n рублей когда ваш баланс становится близок к 0 менее 100 руб производится автопополнение с привязанной карты на сумму равную сумме последнего пополнения если вы пополнили баланс на 500 руб при привязке автоплатежа при достижении около нулевого баланса будет списываться по 500 руб но не более заданного лимита в совокупности если вы хотите отключить подключенный вами автоплатеж просто удалите его на странице баланс одной кнопкой eval rst admonition важно class warning мы не храним данные карт на своей стороне все данные необходимые для повторных транзакций хранятся на стороне платежной системы робокасса списания amvera списывает со счета пользователя средства за каждый работающий контейнер используется поминутная тарификация однако списание происходит раз в час или в момент удаления ресурса детализация детализацию списаний и зачислений находится на странице баланс https cloud amvera ru balance используя переключатель можно отдельно просматривать списания или зачисления за выбранный период balance details img balance details png",
    "metadata": {
        "file_name": "topup.md",
        "section_count": 7,
        "section_1": "Пополнение счета",
        "section_2": "Пополнение счета для юридических лиц",
        "section_3": "Пополнение счета для физических лиц",
        "section_4": "Промокоды",
        "section_5": "Подключение автоплатежа",
        "section_6": "Списания",
        "section_7": "Детализация"
    }
}