{
    "text": "переменные и секреты переменная окружения это текстовая переменная операционной системы в нашем случае контейнера хранящая какую либо информацию — например данные о настройках системы токены пароли и т д amvera cloud позволяет создавать и использовать переменные окружения и секреты eval rst admonition важно class warning чтобы переменные применились нужно перезапустить контейнеры на этапе сборки переменные окружения не доступны добавление переменной или секрета добавление происходит в разделе переменные python config img secrets vars png для добавления переменой секрета необходимо нажать на кнопку создать переменную и заполнить всплывающую форму создания python config img create env png где название имя создаваемой переменной секрета по которому он доступен в системе значение требуемое значение которое должна хранить эта перемеменная секрет доступ к переменным после добавления переменной окружения она будет доступна для чтения следующим образом пример для python python import os my var os environ my var вместо my var нужно подставить имя переменной окружения или секрета который был добавлен через веб интерфейс переменная amvera если приложению нужно различать в каком окружении оно работает amvera или например локально на компьютере разработчика можно использовать переменную окружения amvera в окружении amvera эта переменная задана и имеет значение 1 так чтобы в коде python понять запущена программа локально или в amvera достаточно выполнить python import os amvera var os environ amvera if amvera var 1 print работаю в облаке амвера else print работаю локально отличие секретов от переменных окружения отличие секретов от обычных переменных окружения в том что обычные переменные окружения хранятся открытым текстом в базе данных а секреты хранятся в отдельном хранилище секретов и в базе данных хранится только ссылка на этот секрет секреты подходят для храненения такой конфиденциальной информации как токены и пароли",
    "metadata": {
        "file_name": "variables.md",
        "section_count": 5,
        "section_1": "Переменные и секреты",
        "section_2": "Добавление переменной или секрета",
        "section_3": "Доступ к переменным",
        "section_4": "Переменная AMVERA",
        "section_5": "Отличие секретов от переменных окружения"
    }
}